{
  "annual_div_per_share_stored": 1.68,
  "asset_type": "EQUITY",
  "bq_components": {
    "balance_sheet": 1.0,
    "ceo_quality": 0.0,
    "competitive_moat": 0.0,
    "deal_delay_risk": 0.0,
    "debt_maturity_risk": 0.0,
    "divergence_signal": 0.0,
    "gross_margin_trend": 0.0,
    "growth_trajectory": -1.0,
    "insider_ownership": -1.0,
    "macro_tailwind": 0.0,
    "margin_quality": 0.0,
    "mgmt_capital_allocation": 0.0,
    "reinvestment_runway": 0.0,
    "revenue_quality": 2.0,
    "roic_wacc_spread": 2.0
  },
  "bq_raw": 3.0,
  "business_type": "compounder",
  "business_type_source": "auto",
  "conviction_score": -2.0,
  "created_at": "2026-05-12T20:17:51+00:00",
  "dividend_yield_current": 0.01435,
  "dividend_yield_zscore": null,
  "enterprise_value": 484914715838.0331,
  "eps_fwd": 4.74079,
  "eps_ttm": 3.0,
  "ev_fwd_rev": 7.9827,
  "fcf_ttm": 12733000000.0,
  "fd_direction": "negative",
  "fd_votes": {},
  "flags": [],
  "fs_class": "moderate",
  "fs_quality_base": 57.5,
  "fs_score": 51.5,
  "full_recalc_trigger": "daily_fundamentals_script",
  "fwd_revenue_stored": 60745998336.0,
  "industry": "Communication Equipment",
  "last_daily_update": "2026-05-15T16:29:32+00:00",
  "last_full_calc": "2026-05-15T16:29:32+00:00",
  "manual_overrides": {},
  "market_cap": 462433715838.0331,
  "net_debt_stored": 22481000000.0,
  "owner_earnings_yield": 0.027535,
  "pe_20y_array": [
    27.9436,
    28.0414,
    28.9511,
    29.5789,
    29.6842,
    29.485,
    29.4436,
    28.2947,
    29.1614,
    28.4772,
    28.8982,
    29.7614,
    30.4491,
    30.2772,
    30.014,
    26.3158,
    26.9649,
    26.9649,
    27.4316,
    27.5649,
    27.7895,
    27.2772,
    27.4175,
    27.7614,
    27.4035,
    27.8807,
    27.8667,
    27.7053,
    28.3754,
    28.0737,
    27.593,
    26.7404,
    27.2632,
    27.4035,
    27.2772,
    27.4842,
    27.6842,
    27.814,
    27.2281,
    27.5474,
    27.2456,
    27.6561,
    28.3719,
    28.7123,
    28.8281,
    28.0421,
    27.0316,
    27.2246,
    27.3439,
    27.7263,
    28.2246,
    28.3088,
    29.3684,
    29.1825,
    28.8491,
    28.8947,
    28.986,
    28.8982,
    29.6491,
    30.2632,
    30.7754,
    31.4737,
    31.5088,
    31.0842,
    31.2316,
    30.9684,
    30.4772,
    31.4281,
    32.1053,
    32.2281,
    32.5018,
    33.0877,
    32.1544,
    32.3368,
    33.8842,
    34.6386,
    34.8386,
    35.7439,
    40.5368,
    41.0789
  ],
  "pe_percentile_20y": 97.5,
  "pe_ttm": 39.025,
  "position_layers": {
    "core_fraction": 0.0,
    "core_model": null,
    "core_signal_date": null,
    "tactical_fraction": 0.0,
    "tactical_model": null,
    "tactical_signal_date": null
  },
  "price": 117.07499694824219,
  "quote_type": "EQUITY",
  "roic_5y_avg": 0.25229,
  "sector": "Technology",
  "ticker": "CSCO",
  "updated_at": "2026-05-15T16:29:32+00:00",
  "valuation_tax": -5.0,
  "yield_trap_warning": false
}
