{
  "annual_div_per_share_stored": 0.56,
  "asset_type": "EQUITY",
  "bq_components": {
    "balance_sheet": -2.0,
    "ceo_quality": 0.0,
    "competitive_moat": 0.0,
    "deal_delay_risk": 0.0,
    "debt_maturity_risk": 0.0,
    "divergence_signal": 0.0,
    "gross_margin_trend": -1.0,
    "growth_trajectory": -1.0,
    "insider_ownership": -1.0,
    "macro_tailwind": 0.0,
    "margin_quality": -1.0,
    "mgmt_capital_allocation": 0.0,
    "reinvestment_runway": 0.0,
    "revenue_quality": 2.0,
    "roic_wacc_spread": 1.0
  },
  "bq_raw": -3.0,
  "business_type": "compounder",
  "business_type_source": "auto",
  "conviction_score": -8.0,
  "created_at": "2026-05-12T20:18:04+00:00",
  "data_coverage": {
    "bq_auto_dimensions": {
      "balance_sheet": {
        "inputs_available": [],
        "inputs_missing": [
          "net_debt_ebitda"
        ],
        "score": -2.0,
        "source": "neutral_missing_inputs"
      },
      "ceo_quality": {
        "inputs_available": [],
        "inputs_missing": [],
        "score": 0.0,
        "source": "manual_or_default"
      },
      "competitive_moat": {
        "inputs_available": [],
        "inputs_missing": [],
        "score": 0.0,
        "source": "manual_or_default"
      },
      "deal_delay_risk": {
        "inputs_available": [],
        "inputs_missing": [],
        "score": 0.0,
        "source": "manual_or_default"
      },
      "debt_maturity_risk": {
        "inputs_available": [],
        "inputs_missing": [],
        "score": 0.0,
        "source": "manual_or_default"
      },
      "divergence_signal": {
        "inputs_available": [],
        "inputs_missing": [],
        "score": 0.0,
        "source": "manual_or_default"
      },
      "gross_margin_trend": {
        "inputs_available": [],
        "inputs_missing": [
          "gross_margin_trend"
        ],
        "score": -1.0,
        "source": "neutral_missing_inputs"
      },
      "growth_trajectory": {
        "inputs_available": [],
        "inputs_missing": [
          "revenue_growth"
        ],
        "score": -1.0,
        "source": "neutral_missing_inputs"
      },
      "insider_ownership": {
        "inputs_available": [],
        "inputs_missing": [
          "insider_pct"
        ],
        "score": -1.0,
        "source": "neutral_missing_inputs"
      },
      "macro_tailwind": {
        "inputs_available": [],
        "inputs_missing": [],
        "score": 0.0,
        "source": "manual_or_default"
      },
      "margin_quality": {
        "inputs_available": [],
        "inputs_missing": [
          "revenue_growth",
          "fcf_margin",
          "distribution_coverage_ratio",
          "gross_margin"
        ],
        "score": -1.0,
        "source": "neutral_missing_inputs"
      },
      "mgmt_capital_allocation": {
        "inputs_available": [],
        "inputs_missing": [],
        "score": 0.0,
        "source": "manual_or_default"
      },
      "reinvestment_runway": {
        "inputs_available": [],
        "inputs_missing": [],
        "score": 0.0,
        "source": "manual_or_default"
      },
      "revenue_quality": {
        "inputs_available": [],
        "inputs_missing": [
          "gross_margin",
          "fcf_margin"
        ],
        "score": 2.0,
        "source": "neutral_missing_inputs"
      },
      "roic_wacc_spread": {
        "inputs_available": [],
        "inputs_missing": [
          "roic_proxy",
          "roic"
        ],
        "score": 1.0,
        "source": "neutral_missing_inputs"
      }
    },
    "coverage_ratio": 0.45,
    "fetch_errors": [],
    "fields_missing": [
      "revenue_growth",
      "fcf_margin",
      "gross_margin",
      "net_debt_ebitda",
      "distribution_coverage_ratio",
      "gross_margin_trend",
      "roic_proxy",
      "dividend_yield_5y_mean",
      "dividend_yield_5y_std",
      "revenue_accelerating",
      "insider_pct"
    ],
    "fields_present": [
      "price",
      "market_cap",
      "eps_ttm",
      "eps_fwd",
      "fcf_ttm",
      "net_debt_stored",
      "fwd_revenue_stored",
      "annual_div_per_share_stored",
      "pe_20y_array"
    ],
    "info_available": false,
    "low_coverage_threshold": 0.45,
    "low_data_confidence": true,
    "neutral_zero_policy": "Missing BQ inputs contribute 0 to bq_raw; conviction_score is not re-scaled by coverage.",
    "pe_history": {
      "has_pe_series": true,
      "insufficient_20y": true,
      "legacy_no_meta": true,
      "stored_point_count": 80,
      "target_years": 20,
      "years_available": 0.0
    },
    "statements": {
      "balance": true,
      "cashflow": true,
      "income": true
    },
    "valuation_inputs": {
      "ev_fwd_rev": true,
      "owner_earnings_yield": true,
      "pe_percentile_20y": true,
      "pe_ttm": true
    }
  },
  "dividend_yield_current": 0.020202,
  "dividend_yield_zscore": null,
  "enterprise_value": 19300652947.293625,
  "eps_fwd": 2.1423,
  "eps_ttm": 1.01,
  "ev_fwd_rev": 8.0115,
  "fcf_ttm": -371965000.0,
  "fd_direction": "negative",
  "fd_votes": {},
  "flags": [],
  "fs_class": "moderate_low",
  "fs_quality_base": 42.5,
  "fs_score": 31.5,
  "full_recalc_trigger": "daily_fundamentals_script",
  "fwd_revenue_stored": 2409103872.0,
  "industry": "Rental & Leasing Services",
  "last_daily_update": "2026-05-18T20:08:18+00:00",
  "last_full_calc": "2026-05-15T16:29:56+00:00",
  "manual_overrides": {},
  "market_cap": 10976907947.293625,
  "missing_fields": [
    "distribution_coverage_ratio",
    "dividend_yield_5y_mean",
    "dividend_yield_5y_std",
    "fcf_margin",
    "gross_margin",
    "gross_margin_trend",
    "info:empty",
    "insider_pct",
    "net_debt_ebitda",
    "pe_history:insufficient_20y (0.0y)",
    "revenue_accelerating",
    "revenue_growth",
    "roic_proxy"
  ],
  "net_debt_stored": 8323745000.0,
  "owner_earnings_yield": -0.033886,
  "pe_20y_array": [
    32.1852,
    31.8056,
    31.9074,
    31.8148,
    31.5,
    31.6204,
    31.9444,
    32.4537,
    32.4074,
    33.2037,
    32.8148,
    32.8148,
    33.0,
    33.463,
    33.6019,
    31.0093,
    31.3704,
    30.7778,
    31.3889,
    31.2593,
    31.6852,
    31.7593,
    31.9074,
    30.6481,
    31.463,
    30.0833,
    29.7222,
    29.8796,
    29.8704,
    30.2222,
    29.6667,
    29.4167,
    29.2407,
    29.2037,
    28.8148,
    28.5278,
    28.5556,
    28.5648,
    28.3796,
    28.4167,
    28.287,
    28.4259,
    28.5926,
    28.787,
    28.4074,
    27.8796,
    27.7315,
    27.9352,
    28.2315,
    28.3426,
    28.8889,
    28.3241,
    29.2037,
    29.8426,
    29.713,
    30.037,
    30.5648,
    30.1389,
    29.9444,
    30.3056,
    30.1574,
    29.9444,
    30.0463,
    30.3056,
    29.8611,
    29.8241,
    29.5,
    29.5463,
    30.0278,
    29.6389,
    28.5185,
    28.6852,
    28.6759,
    26.7593,
    25.9259,
    24.8611,
    25.5463,
    25.1852,
    25.4167,
    25.787
  ],
  "pe_percentile_20y": 8.75,
  "pe_ttm": 27.4455,
  "position_layers": {
    "core_fraction": 0.0,
    "core_model": null,
    "core_signal_date": null,
    "tactical_fraction": 0.0,
    "tactical_model": null,
    "tactical_signal_date": null
  },
  "price": 27.719999313354492,
  "quote_type": "EQUITY",
  "roic_5y_avg": 0.109069996,
  "sector": "Industrials",
  "ticker": "EFN.TO",
  "updated_at": "2026-05-18T20:08:18+00:00",
  "valuation_tax": -5.0,
  "yield_trap_warning": false
}
